bf2fj/__init__.py
bf2fj/bf2fj_cli.py
bf2fj/bf2fj_compiler.py
bf2fj/bf_classes.py
bf2fj/compiler_exceptions.py
bf2fj/flipjump_output_format.fj
bf2fj-1.0.2.dist-info/LICENSE
bf2fj-1.0.2.dist-info/METADATA
bf2fj-1.0.2.dist-info/WHEEL
bf2fj-1.0.2.dist-info/entry_points.txt
bf2fj-1.0.2.dist-info/RECORD
